LICENSE.txt
MANIFEST.in
README.md
runner.py
setup.py
Subraminion.egg-info/PKG-INFO
Subraminion.egg-info/SOURCES.txt
Subraminion.egg-info/dependency_links.txt
Subraminion.egg-info/entry_points.txt
Subraminion.egg-info/top_level.txt
subraminion/__init__.py
subraminion/subraminion.py