Metadata-Version: 1.0
Name: Subraminion
Version: 0.0.3a
Summary: A nifty console tool to find / delete duplicate files.
Home-page: https://github.com/sandeepraju/subraminion
Author: Sandeep Raju
Author-email: me@sandeepraju.in
License: The MIT License (MIT)
